vpdq.cpython-39-darwin.so
vpdq-0.0.1.dist-info/LICENSE
vpdq-0.0.1.dist-info/METADATA
vpdq-0.0.1.dist-info/WHEEL
vpdq-0.0.1.dist-info/top_level.txt
vpdq-0.0.1.dist-info/RECORD
