Metadata-Version: 2.1
Name: vpdq
Version: 0.0.1
Summary: Python bindings for Facebook VPDQ hash
Author: Facebook
Author-email: threatexchange@fb.com
License: BSD
Requires-Dist: numpy
Requires-Dist: cython
Requires-Dist: opencv-python
Requires-Dist: opencv-python-headless
